simple_slack_send/VERSION
simple_slack_send/__init__.py
simple_slack_send/__main__.py
simple_slack_send/cli.py
simple_slack_send/loader.py
Simple_Slack_Send-0.1.2.dist-info/METADATA
Simple_Slack_Send-0.1.2.dist-info/WHEEL
Simple_Slack_Send-0.1.2.dist-info/entry_points.txt
Simple_Slack_Send-0.1.2.dist-info/top_level.txt
Simple_Slack_Send-0.1.2.dist-info/RECORD
