Metadata-Version: 2.1
Name: Simple-Slack-Send
Version: 0.1.2
Summary: Simple Slack Send - send Slack notifications in CI pipelines
Home-page: http://github.com/wlatanowicz/simple-slack-send
Author: Wiktor Latanowicz
Author-email: simple-slack-send@wiktor.latanowicz.com
License: MIT
Classifier: Programming Language :: Python :: 3
Classifier: License :: OSI Approved :: MIT License
Classifier: Operating System :: OS Independent
Requires-Python: >=3.6
Requires-Dist: Jinja2 (>=3.1.2)
Requires-Dist: click (>=8.1.3)
Requires-Dist: requests (>=2.27.1)
